{
    "language": "slk",
    "editor": "Marek Vician",
    "eltec_edition_str": "ELTeC edícia",
    "srced": {
        "title": "Červené víno",
        "publisher": "Tatran",
        "pub_place": "Bratislava",
        "pub_date": "1968"
    },
    "firsted": {
        "pub_date": "1948"
    },
    "authors": [
        {
            "first_name": "František",
            "last_name": "Hečko",
            "birth_date": "1905",
            "death_date": "1960",
            "ref": "viaf:42311620"
        }
    ],
    "languages": [
        "slo"
    ],
    "encoding_lvl": "eltec-1",
    "gender": "M",
    "canonicity": "unspecified"
}
